rondterre/__init__.py
rondterre/const.py
rondterre/file_utils.py
rondterre/gen_string.py
rondterre/misc.py
rondterre-0.0.2.dist-info/METADATA
rondterre-0.0.2.dist-info/RECORD
rondterre-0.0.2.dist-info/WHEEL
rondterre-0.0.2.dist-info/top_level.txt
