Metadata-Version: 2.1
Name: rondterre
Version: 0.0.2
Summary: Some personal python3 snippet
Home-page: https://github.com/Theodoric008
Author: theodoric008
Author-email: liujiashu2333@qq.com
License: UNKNOWN
Platform: UNKNOWN
Classifier: Programming Language :: Python :: 3
Classifier: License :: OSI Approved :: MIT License
Classifier: Operating System :: OS Independent
